agentgui/__init__.py
agentgui/gui_agent.py
agentgui/model.py
agentgui/playwright_agent.py
agentgui-0.0.2.dist-info/METADATA
agentgui-0.0.2.dist-info/WHEEL
agentgui-0.0.2.dist-info/entry_points.txt
agentgui-0.0.2.dist-info/RECORD
