Metadata-Version: 2.1
Name: agentgui
Version: 0.0.2
Summary: agents based on pyautogui
Home-page: https://github.com/santhosh/
License: MIT
Author: Kammari Santhosh
Requires-Python: >=3.10,<4.0
Classifier: License :: OSI Approved :: MIT License
Classifier: Programming Language :: Python :: 3
Classifier: Programming Language :: Python :: 3.10
Classifier: Programming Language :: Python :: 3.11
Classifier: Programming Language :: Python :: 3.12
Classifier: Programming Language :: Python :: 3.13
Requires-Dist: pyautogui (>=0.9.54,<0.10.0)
Project-URL: Repository, https://github.com/santhosh/
